rolca/__about__.py
rolca/__init__.py
rolca/urls.py
rolca/core/__init__.py
rolca/core/admin.py
rolca/core/apps.py
rolca/core/models.py
rolca/core/urls.py
rolca/core/views.py
rolca/core/api/__init__.py
rolca/core/api/permissions.py
rolca/core/api/serializers.py
rolca/core/api/urls.py
rolca/core/api/viewsets.py
rolca/core/locale/sl/LC_MESSAGES/django.mo
rolca/core/locale/sl/LC_MESSAGES/django.po
rolca/core/migrations/0001_initial.py
rolca/core/migrations/0002_add_contest_description.py
rolca/core/migrations/0003_contest_login_required.py
rolca/core/migrations/0004_author_email.py
rolca/core/migrations/0005_nonrequired_user.py
rolca/core/migrations/0006_photo_title_not_required.py
rolca/core/migrations/__init__.py
rolca/frontend/__init__.py
rolca/frontend/apps.py
rolca/frontend/context_processors.py
rolca/frontend/decorators.py
rolca/frontend/forms.py
rolca/frontend/settings.py
rolca/frontend/urls.py
rolca/frontend/validators.py
rolca/frontend/views.py
rolca/frontend/locale/sl/LC_MESSAGES/django.mo
rolca/frontend/locale/sl/LC_MESSAGES/django.po
rolca/frontend/static/frontend/css/frontend.css
rolca/frontend/static/materialize/css/materialize.min.css
rolca/frontend/static/materialize/fonts/roboto/Roboto-Bold.eot
rolca/frontend/static/materialize/fonts/roboto/Roboto-Bold.ttf
rolca/frontend/static/materialize/fonts/roboto/Roboto-Bold.woff
rolca/frontend/static/materialize/fonts/roboto/Roboto-Bold.woff2
rolca/frontend/static/materialize/fonts/roboto/Roboto-Light.eot
rolca/frontend/static/materialize/fonts/roboto/Roboto-Light.ttf
rolca/frontend/static/materialize/fonts/roboto/Roboto-Light.woff
rolca/frontend/static/materialize/fonts/roboto/Roboto-Light.woff2
rolca/frontend/static/materialize/fonts/roboto/Roboto-Medium.eot
rolca/frontend/static/materialize/fonts/roboto/Roboto-Medium.ttf
rolca/frontend/static/materialize/fonts/roboto/Roboto-Medium.woff
rolca/frontend/static/materialize/fonts/roboto/Roboto-Medium.woff2
rolca-0.0.9.dist-info/DESCRIPTION.rst
rolca-0.0.9.dist-info/METADATA
rolca-0.0.9.dist-info/RECORD
rolca-0.0.9.dist-info/WHEEL
rolca-0.0.9.dist-info/metadata.json
rolca-0.0.9.dist-info/top_level.txt
