Metadata-Version: 2.0
Name: rolca
Version: 0.0.9
Summary: Open source platform for uploading photos
Home-page: https://github.com/dblenkus/rolca
Author: Domen Blenkuš
Author-email: domen@blenkus.com
License: Apache License (2.0)
Platform: UNKNOWN
Classifier: Development Status :: 2 - Pre-Alpha
Classifier: Environment :: Web Environment
Classifier: Framework :: Django
Classifier: License :: OSI Approved :: Apache Software License
Classifier: Operating System :: OS Independent
Classifier: Programming Language :: Python
Classifier: Programming Language :: Python :: 3
Classifier: Programming Language :: Python :: 3.4
Classifier: Programming Language :: Python :: 3.5
Classifier: Topic :: Internet :: WWW/HTTP
Classifier: Topic :: Internet :: WWW/HTTP :: Dynamic Content
Classifier: Topic :: Internet :: WWW/HTTP :: WSGI
Classifier: Topic :: Software Development :: Libraries :: Python Modules
Requires-Dist: Django (>=1.10,<1.11a1)
Requires-Dist: Pillow (>=3.0.0)
Requires-Dist: djangorestframework (>=3.4.0)
Requires-Dist: psycopg2 (>=2.5.0)
Provides-Extra: docs
Requires-Dist: sphinx (>=1.3.2); extra == 'docs'
Requires-Dist: sphinx-rtd-theme; extra == 'docs'
Provides-Extra: package
Requires-Dist: twine; extra == 'package'
Requires-Dist: wheel; extra == 'package'
Provides-Extra: test
Requires-Dist: check-manifest; extra == 'test'
Requires-Dist: coverage (>=4.2); extra == 'test'
Requires-Dist: isort; extra == 'test'
Requires-Dist: mock (>=1.3.0); extra == 'test'
Requires-Dist: pycodestyle (>=2.1.0); extra == 'test'
Requires-Dist: pydocstyle (>=1.0.0); extra == 'test'
Requires-Dist: pylint (>=1.6.4); extra == 'test'
Requires-Dist: readme-renderer; extra == 'test'
